{
  "Analytics": "Analisi",
  "Auth.components.Oops.text": "Il tuo account è stato sospeso.",
  "Auth.components.Oops.text.admin": "Se si tratta di un errore, contatta il tuo amministratore.",
  "Auth.components.Oops.title": "Oops...",
  "Auth.form.active.label": "Attivo",
  "Auth.form.button.forgot-password": "Invia Email",
  "Auth.form.button.go-home": "TORNA ALLA HOME",
  "Auth.form.button.login": "Accedi",
  "Auth.form.button.login.providers.error": "Non possiamo connetterti tramite il provider selezionato.",
  "Auth.form.button.login.strapi": "Accedi tramite Strapi",
  "Auth.form.button.password-recovery": "Recupero Password",
  "Auth.form.button.register": "Iniziamo",
  "Auth.form.confirmPassword.label": "Conferma Password",
  "Auth.form.currentPassword.label": "Password Attuale",
  "Auth.form.email.label": "Email",
  "Auth.form.email.placeholder": "es. kai@doe.com",
  "Auth.form.error.blocked": "Il tuo account è stato bloccato dall'amministratore.",
  "Auth.form.error.code.provide": "Codice fornito non corretto.",
  "Auth.form.error.confirmed": "L'email del tuo account non è confermata.",
  "Auth.form.error.email.invalid": "Questa email non è valida.",
  "Auth.form.error.email.provide": "Per favore fornisci il tuo nome utente o la tua email.",
  "Auth.form.error.email.taken": "Email già in uso.",
  "Auth.form.error.invalid": "Identificatore o password non validi.",
  "Auth.form.error.params.provide": "Parametri forniti non corretti.",
  "Auth.form.error.password.format": "La tua password non può contenere il simbolo $ più di tre volte.",
  "Auth.form.error.password.local": "Questo utente non ha mai impostato una password locale, accedi tramite il provider utilizzato durante la creazione dell'account.",
  "Auth.form.error.password.matching": "Le password non corrispondono.",
  "Auth.form.error.password.provide": "Per favore fornisci la tua password.",
  "Auth.form.error.ratelimit": "Troppi tentativi, riprova tra un minuto.",
  "Auth.form.error.user.not-exist": "Questa email non esiste.",
  "Auth.form.error.username.taken": "Nome utente già in uso.",
  "Auth.form.firstname.label": "Nome",
  "Auth.form.firstname.placeholder": "es. Kai",
  "Auth.form.forgot-password.email.label": "Inserisci la tua email",
  "Auth.form.forgot-password.email.label.success": "Email inviata con successo a",
  "Auth.form.lastname.label": "Cognome",
  "Auth.form.lastname.placeholder": "es. Doe",
  "Auth.form.password.hide-password": "Nascondi password",
  "Auth.form.password.hint": "Deve contenere almeno 8 caratteri, 1 maiuscola, 1 minuscola e 1 numero",
  "Auth.form.password.show-password": "Mostra password",
  "Auth.form.register.news.label": "Tienimi aggiornato sulle nuove funzionalità e i prossimi miglioramenti (facendo ciò accetti i {terms} e la {policy}).",
  "Auth.form.register.subtitle": "Le credenziali sono usate solo per autenticarsi in Strapi. Tutti i dati salvati saranno memorizzati nel tuo database.",
  "Auth.form.rememberMe.label": "Ricordami",
  "Auth.form.username.label": "Nome utente",
  "Auth.form.username.placeholder": "es. Kai_Doe",
  "Auth.form.welcome.subtitle": "Accedi al tuo account Strapi",
  "Auth.form.welcome.title": "Benvenuto in Strapi!",
  "Auth.link.forgot-password": "Password dimenticata?",
  "Auth.link.ready": "Pronto per accedere?",
  "Auth.link.signin": "Accedi",
  "Auth.link.signin.account": "Hai già un account?",
  "Auth.login.sso.divider": "O accedi con",
  "Auth.login.sso.loading": "Caricamento provider...",
  "Auth.login.sso.subtitle": "Accedi al tuo account tramite SSO",
  "Auth.privacy-policy-agreement.policy": "politica sulla privacy",
  "Auth.privacy-policy-agreement.terms": "termini",
  "Auth.reset-password.title": "Reimposta password",
  "Content Manager": "Gestore dei Contenuti",
  "Content Type Builder": "Costruttore di Tipi di Contenuto",
  "Documentation": "Documentazione",
  "Email": "Email",
  "Files Upload": "Caricamento File",
  "HomePage.head.title": "Homepage",
  "HomePage.header.title": "Ciao {name}",
  "HomePage.header.subtitle": "Benvenuto nel tuo pannello di amministrazione",
  "HomePage.widget.loading": "Caricamento contenuto del widget",
  "HomePage.widget.error": "Impossibile caricare il contenuto del widget.",
  "HomePage.widget.no-data": "Nessun contenuto trovato.",
  "HomePage.widget.no-permissions": "Non hai il permesso di vedere questo widget",
  "Media Library": "Libreria Multimediale",
  "New entry": "Nuova voce",
  "Password": "Password",
  "Provider": "Provider",
  "ResetPasswordToken": "TokenReimpostaPassword",
  "Role": "Ruolo",
  "Roles & Permissions": "Ruoli & Permessi",
  "Roles.ListPage.notification.delete-all-not-allowed": "Alcuni ruoli non possono essere eliminati poiché sono associati a degli utenti",
  "Roles.ListPage.notification.delete-not-allowed": "Un ruolo non può essere eliminato se associato a degli utenti",
  "Roles.RoleRow.select-all": "Seleziona {name} per azioni di massa",
  "Roles.RoleRow.user-count": "{number, plural, =0 {# utente} one {# utente} other {# utenti}}",
  "Roles.components.List.empty.withSearch": "Non c'è nessun ruolo corrispondente alla ricerca ({search})...",
  "Settings.PageTitle": "Impostazioni — {name}",
  "Settings.apiTokens.ListView.headers.createdAt": "Creato il",
  "Settings.apiTokens.ListView.headers.description": "Descrizione",
  "Settings.apiTokens.ListView.headers.lastUsedAt": "Ultimo utilizzo",
  "Settings.apiTokens.ListView.headers.name": "Nome",
  "Settings.apiTokens.ListView.headers.type": "Tipo di token",
  "Settings.apiTokens.addFirstToken": "Aggiungi il tuo primo Token API",
  "Settings.apiTokens.addNewToken": "Aggiungi nuovo Token API",
  "Settings.apiTokens.create": "Crea nuovo Token API",
  "Settings.apiTokens.createPage.BoundRoute.title": "Percorso vincolato a",
  "Settings.apiTokens.createPage.permissions.description": "Solo le azioni vincolate a un percorso sono elencate di seguito.",
  "Settings.apiTokens.createPage.permissions.header.hint": "Seleziona le azioni dell'applicazione o del plugin e clicca sull'icona dell'ingranaggio per visualizzare il percorso vincolato",
  "Settings.apiTokens.createPage.permissions.header.title": "Impostazioni avanzate",
  "Settings.apiTokens.createPage.permissions.title": "Permessi",
  "Settings.apiTokens.createPage.title": "Crea Token API",
  "Settings.apiTokens.description": "Elenco dei token generati per consumare l'API",
  "Settings.apiTokens.emptyStateLayout": "Non hai ancora nessun contenuto...",
  "Settings.apiTokens.regenerate": "Rigenera",
  "Settings.apiTokens.title": "Token API",
  "Settings.apiTokens.lastHour": "ultima ora",
  "Settings.application.customization": "Personalizzazione",
  "Settings.application.customization.auth-logo.carousel-hint": "Sostituisci il logo nelle pagine di autenticazione",
  "Settings.application.customization.carousel-hint": "Cambia il logo del pannello di amministrazione (Dimensione massima: {dimension}x{dimension}, Dimensione massima file: {size}KB)",
  "Settings.application.customization.carousel-slide.label": "Slide del logo",
  "Settings.application.customization.carousel.auth-logo.title": "Logo di autenticazione",
  "Settings.application.customization.carousel.change-action": "Cambia logo",
  "Settings.application.customization.carousel.menu-logo.title": "Logo del menu",
  "Settings.application.customization.carousel.reset-action": "Reimposta logo",
  "Settings.application.customization.carousel.title": "Logo",
  "Settings.application.customization.menu-logo.carousel-hint": "Sostituisci il logo nella navigazione principale",
  "Settings.application.customization.modal.cancel": "Annulla",
  "Settings.application.customization.modal.pending": "Logo in attesa",
  "Settings.application.customization.modal.pending.card-badge": "immagine",
  "Settings.application.customization.modal.pending.choose-another": "Scegli un altro logo",
  "Settings.application.customization.modal.pending.subtitle": "Gestisci il logo scelto prima di caricarlo",
  "Settings.application.customization.modal.pending.title": "Logo pronto per il caricamento",
  "Settings.application.customization.modal.pending.upload": "Carica logo",
  "Settings.application.customization.modal.tab.label": "Come vuoi caricare i tuoi asset?",
  "Settings.application.customization.modal.upload": "Carica logo",
  "Settings.application.customization.modal.upload.cta.browse": "Sfoglia file",
  "Settings.application.customization.modal.upload.drag-drop": "Trascina e rilascia qui o",
  "Settings.application.customization.modal.upload.error-format": "Formato caricato errato (formati accettati: solo jpeg, jpg, png, svg).",
  "Settings.application.customization.modal.upload.error-network": "Errore di rete",
  "Settings.application.customization.modal.upload.error-size": "Il file caricato è troppo grande (dimensione massima: {dimension}x{dimension}, dimensione massima file: {size}KB)",
  "Settings.application.customization.modal.upload.file-validation": "Dimensione massima: {dimension}x{dimension}, Dimensione massima: {size}KB",
  "Settings.application.customization.modal.upload.from-computer": "Dal computer",
  "Settings.application.customization.modal.upload.from-url": "Da URL",
  "Settings.application.customization.modal.upload.from-url.input-label": "URL",
  "Settings.application.customization.modal.upload.next": "Avanti",
  "Settings.application.customization.size-details": "Dimensione massima: {dimension}×{dimension}, Dimensione massima file: {size}KB",
  "Settings.application.description": "Informazioni globali del pannello di amministrazione",
  "Settings.application.edition-title": "edizione attuale",
  "Settings.application.ee-or-ce": "{communityEdition, select, true {Community Edition} other {Enterprise Edition}}",
  "Settings.application.ee.admin-seats.add-seats": "Gestisci posti",
  "Settings.application.ee.admin-seats.support": "Contatta le vendite",
  "Settings.application.ee.admin-seats.at-limit-tooltip": "Al limite: aggiungi posti per invitare più utenti",
  "Settings.application.ee.admin-seats.count": "{enforcementUserCount}/{permittedSeats}",
  "Settings.application.get-help": "Ottieni aiuto",
  "Settings.application.link-pricing": "Vedi tutti i piani di prezzo",
  "Settings.application.link-upgrade": "Aggiorna il tuo pannello di amministrazione",
  "Settings.application.node-version": "versione node",
  "Settings.application.strapi-version": "Versione Strapi",
  "Settings.application.strapiVersion": "Versione Strapi",
  "Settings.application.title": "Panoramica",
  "Settings.error": "Errore",
  "Settings.global": "Impostazioni Globali",
  "Settings.permissions": "Pannello di amministrazione",
  "Settings.permissions.auditLogs.action": "Azione",
  "Settings.permissions.auditLogs.admin.auth.success": "Accesso admin",
  "Settings.permissions.auditLogs.admin.logout": "Logout admin",
  "Settings.permissions.auditLogs.component.create": "Crea componente",
  "Settings.permissions.auditLogs.component.delete": "Elimina componente",
  "Settings.permissions.auditLogs.component.update": "Aggiorna componente",
  "Settings.permissions.auditLogs.content-type.create": "Crea tipo di contenuto",
  "Settings.permissions.auditLogs.content-type.delete": "Elimina tipo di contenuto",
  "Settings.permissions.auditLogs.content-type.update": "Aggiorna tipo di contenuto",
  "Settings.permissions.auditLogs.date": "Data",
  "Settings.permissions.auditLogs.details": "Dettagli del Log",
  "Settings.permissions.auditLogs.entry.create": "Crea voce{model, select, undefined {} other { ({model})}}",
  "Settings.permissions.auditLogs.entry.delete": "Elimina voce{model, select, undefined {} other { ({model})}}",
  "Settings.permissions.auditLogs.entry.publish": "Pubblica voce {model, select, undefined {} other {({model})}}",
  "Settings.permissions.auditLogs.entry.unpublish": "Annulla pubblicazione voce{model, select, undefined {} other { ({model})}}",
  "Settings.permissions.auditLogs.entry.update": "Aggiorna voce{model, select, undefined {} other { ({model})}}",
  "Settings.permissions.auditLogs.filters.combobox.aria-label": "Cerca e seleziona un'opzione per filtrare",
  "Settings.permissions.auditLogs.listview.header.subtitle": "Log di tutte le attività avvenute nel tuo ambiente",
  "Settings.permissions.auditLogs.not-available": "I Log di Audit sono disponibili solo come parte di un piano a pagamento. Aggiorna per ottenere una visualizzazione ricercabile e filtrabile di tutte le attività.",
  "Settings.permissions.auditLogs.media.create": "Crea media",
  "Settings.permissions.auditLogs.media.delete": "Elimina media",
  "Settings.permissions.auditLogs.media.update": "Aggiorna media",
  "Settings.permissions.auditLogs.payload": "Payload",
  "Settings.permissions.auditLogs.permission.create": "Crea permesso",
  "Settings.permissions.auditLogs.permission.delete": "Elimina permesso",
  "Settings.permissions.auditLogs.permission.update": "Aggiorna permesso",
  "Settings.permissions.auditLogs.role.create": "Crea ruolo",
  "Settings.permissions.auditLogs.role.delete": "Elimina ruolo",
  "Settings.permissions.auditLogs.role.update": "Aggiorna ruolo",
  "Settings.permissions.auditLogs.user": "Utente",
  "Settings.permissions.auditLogs.user.create": "Crea utente",
  "Settings.permissions.auditLogs.user.delete": "Elimina utente",
  "Settings.permissions.auditLogs.user.fullname": "{firstname} {lastname}",
  "Settings.permissions.auditLogs.user.update": "Aggiorna utente",
  "Settings.permissions.auditLogs.userId": "ID Utente",
  "Settings.permissions.category": "Impostazioni dei permessi per {category}",
  "Settings.permissions.category.plugins": "Impostazioni dei permessi per il plugin {category}",
  "Settings.permissions.conditions.anytime": "In qualsiasi momento",
  "Settings.permissions.conditions.apply": "Applica",
  "Settings.permissions.conditions.can": "Può",
  "Settings.permissions.conditions.conditions": "Condizioni",
  "Settings.permissions.conditions.define-conditions": "Definisci condizioni",
  "Settings.permissions.conditions.links": "Collegamenti",
  "Settings.permissions.conditions.no-actions": "Devi prima selezionare le azioni (crea, leggi, aggiorna, ...) prima di definire le condizioni su di esse.",
  "Settings.permissions.conditions.none-selected": "In qualsiasi momento",
  "Settings.permissions.conditions.or": "O",
  "Settings.permissions.conditions.when": "Quando",
  "Settings.permissions.select-all-by-permission": "Seleziona tutti i permessi {label}",
  "Settings.permissions.select-by-permission": "Seleziona il permesso {label}",
  "Settings.permissions.users.active": "Attivo",
  "Settings.permissions.users.create": "Invita nuovo utente",
  "Settings.permissions.users.email": "Email",
  "Settings.permissions.users.firstname": "Nome",
  "Settings.permissions.users.form.sso": "Connetti con SSO",
  "Settings.permissions.users.sso.provider.error": "Si è verificato un errore durante la richiesta delle impostazioni SSO",
  "Settings.permissions.users.form.sso.description": "Quando abilitato (ON), gli utenti possono accedere tramite SSO",
  "Settings.permissions.users.inactive": "Inattivo",
  "Settings.permissions.users.lastname": "Cognome",
  "Settings.permissions.users.listview.header.subtitle": "Tutti gli utenti che hanno accesso al pannello di amministrazione Strapi",
  "Settings.permissions.users.roles": "Ruoli",
  "Settings.permissions.users.strapi-author": "Autore",
  "Settings.permissions.users.strapi-editor": "Editor",
  "Settings.permissions.users.strapi-super-admin": "Super Admin",
  "Settings.permissions.users.tabs.label": "Permessi delle schede",
  "Settings.permissions.users.user-status": "Stato utente",
  "Settings.permissions.users.username": "Nome utente",
  "Settings.profile.form.notify.data.loaded": "I tuoi dati del profilo sono stati caricati",
  "Settings.profile.form.section.experience.clear.select": "Cancella la lingua dell'interfaccia selezionata",
  "Settings.profile.form.section.experience.here": "qui",
  "Settings.profile.form.section.experience.interfaceLanguage": "Lingua dell'interfaccia",
  "Settings.profile.form.section.experience.interfaceLanguage.hint": "Questo mostrerà solo la tua interfaccia nella lingua scelta.",
  "Settings.profile.form.section.experience.interfaceLanguageHelp": "Le modifiche alle preferenze si applicheranno solo a te. Maggiori informazioni sono disponibili {here}.",
  "Settings.profile.form.section.experience.mode.hint": "Visualizza la tua interfaccia nella modalità scelta.",
  "Settings.profile.form.section.experience.mode.label": "Modalità interfaccia",
  "Settings.profile.form.section.experience.mode.option-label": "Modalità {name}",
  "Settings.profile.form.section.experience.mode.option-system-label": "Usa impostazioni di sistema",
  "Settings.profile.form.section.experience.title": "Esperienza",
  "Settings.profile.form.section.head.title": "Profilo utente",
  "Settings.profile.form.section.profile.page.title": "Pagina del profilo",
  "Settings.roles.create.description": "Definisci i diritti assegnati al ruolo",
  "Settings.roles.create.title": "Crea un ruolo",
  "Settings.roles.created": "Ruolo creato",
  "Settings.roles.edit.title": "Modifica un ruolo",
  "Settings.roles.form.button.users-with-role": "{number, plural, =0 {# utenti} one {# utente} other {# utenti}} con questo ruolo",
  "Settings.roles.form.created": "Creato",
  "Settings.roles.form.description": "Nome e descrizione del ruolo",
  "Settings.roles.form.permission.property-label": "Permessi {label}",
  "Settings.roles.form.permissions.attributesPermissions": "Permessi dei campi",
  "Settings.roles.form.permissions.create": "Crea",
  "Settings.roles.form.permissions.delete": "Elimina",
  "Settings.roles.form.permissions.publish": "Pubblica",
  "Settings.roles.form.permissions.read": "Leggi",
  "Settings.roles.form.permissions.update": "Aggiorna",
  "Settings.roles.list.button.add": "Aggiungi nuovo ruolo",
  "Settings.roles.list.description": "Elenco dei ruoli",
  "Settings.roles.title.singular": "ruolo",
  "Settings.sso.description": "Configura le impostazioni per la funzionalità Single Sign-On.",
  "Settings.sso.form.defaultRole.description": "Assegnerà il nuovo utente autenticato al ruolo selezionato",
  "Settings.sso.form.defaultRole.description-not-allowed": "Devi avere il permesso di leggere i ruoli di amministrazione",
  "Settings.sso.form.defaultRole.label": "Ruolo predefinito",
  "Settings.sso.form.localAuthenticationLock.label": "Blocco dell'autenticazione locale",
  "Settings.sso.form.localAuthenticationLock.description": "Seleziona i ruoli per i quali vuoi disabilitare l'autenticazione locale",
  "Settings.sso.form.registration.description": "Crea un nuovo utente al login SSO se non esiste un account",
  "Settings.sso.form.registration.label": "Auto-registrazione",
  "Settings.sso.title": "Single Sign-On",
  "Settings.sso.not-available": "SSO è disponibile solo come parte di un piano a pagamento. Aggiorna per configurare metodi aggiuntivi di accesso e registrazione per il tuo pannello di amministrazione.",
  "Settings.content-history.title": "Cronologia dei Contenuti",
  "Settings.content-history.description": "Ottieni maggior controllo su ogni fase del ciclo di vita dei tuoi contenuti.",
  "Settings.content-history.not-available": "La Cronologia dei Contenuti è disponibile solo come parte di un piano a pagamento. Aggiorna per ottenere il pieno controllo sul ciclo di vita dei tuoi contenuti.",
  "Settings.tokens.Button.cancel": "Annulla",
  "Settings.tokens.Button.regenerate": "Rigenera",
  "Settings.tokens.ListView.headers.createdAt": "Creato il",
  "Settings.tokens.ListView.headers.description": "Descrizione",
  "Settings.tokens.ListView.headers.lastUsedAt": "Ultimo utilizzo",
  "Settings.tokens.ListView.headers.name": "Nome",
  "Settings.tokens.RegenerateDialog.title": "Rigenera token",
  "Settings.tokens.copy.editMessage": "Per motivi di sicurezza, puoi vedere il tuo token solo una volta.",
  "Settings.tokens.copy.editTitle": "Questo token non è più accessibile.",
  "Settings.tokens.copy.lastWarning": "Assicurati di copiare questo token, non potrai più vederlo!",
  "Settings.tokens.duration.30-days": "30 giorni",
  "Settings.tokens.duration.7-days": "7 giorni",
  "Settings.tokens.duration.90-days": "90 giorni",
  "Settings.tokens.duration.expiration-date": "Data di scadenza",
  "Settings.tokens.duration.unlimited": "Illimitato",
  "Settings.tokens.form.description": "Descrizione",
  "Settings.tokens.form.duration": "Durata del token",
  "Settings.tokens.form.name": "Nome",
  "Settings.tokens.form.type": "Tipo di token",
  "Settings.tokens.notification.copied": "Token copiato negli appunti.",
  "Settings.tokens.popUpWarning.message": "Sei sicuro di voler rigenerare questo token?",
  "Settings.tokens.regenerate": "Rigenera",
  "Settings.tokens.types.custom": "Personalizzato",
  "Settings.tokens.types.full-access": "Accesso completo",
  "Settings.tokens.types.read-only": "Sola lettura",
  "Settings.transferTokens.ListView.headers.type": "Tipo di token",
  "Settings.transferTokens.addFirstToken": "Aggiungi il tuo primo Token di Trasferimento",
  "Settings.transferTokens.addNewToken": "Aggiungi nuovo Token di Trasferimento",
  "Settings.transferTokens.create": "Crea nuovo Token di Trasferimento",
  "Settings.transferTokens.createPage.title": "Crea Token di Trasferimento",
  "Settings.transferTokens.description": "Elenco dei token di trasferimento generati",
  "Settings.transferTokens.emptyStateLayout": "Non hai ancora nessun contenuto...",
  "Settings.transferTokens.title": "Token di Trasferimento",
  "Settings.webhooks.create": "Crea un webhook",
  "Settings.webhooks.create.header": "Crea nuova intestazione",
  "Settings.webhooks.created": "Webhook creato",
  "Settings.webhooks.event.publish-tooltip": "Questo evento esiste solo per i contenuti con sistema Bozza/Pubblicazione abilitato",
  "Settings.webhooks.event.select": "Seleziona evento",
  "Settings.webhooks.events.isLoading": "Caricamento eventi",
  "Settings.webhooks.events.create": "Crea",
  "Settings.webhooks.events.update": "Aggiorna",
  "Settings.webhooks.events.delete": "Elimina webhook",
  "Settings.webhooks.form.events": "Eventi",
  "Settings.webhooks.form.headers": "Intestazioni",
  "Settings.webhooks.form.url": "URL",
  "Settings.webhooks.headers.remove": "Rimuovi riga intestazione {number}",
  "Settings.webhooks.key": "Chiave",
  "Settings.webhooks.list.button.add": "Crea nuovo webhook",
  "Settings.webhooks.list.description": "Ricevi notifiche POST delle modifiche",
  "Settings.webhooks.list.empty.description": "Nessun webhook trovato",
  "Settings.webhooks.list.empty.link": "Vedi la nostra documentazione",
  "Settings.webhooks.list.empty.title": "Non ci sono ancora webhook",
  "Settings.webhooks.list.th.actions": "azioni",
  "Settings.webhooks.list.th.status": "stato",
  "Settings.webhooks.list.loading.success": "I webhook sono stati caricati",
  "Settings.webhooks.singular": "webhook",
  "Settings.webhooks.title": "Webhook",
  "Settings.webhooks.to.delete": "{webhooksToDeleteLength, plural, one {# webhook} other {# webhook}} selezionati",
  "Settings.webhooks.trigger": "Attiva",
  "Settings.webhooks.trigger.cancel": "Annulla attivazione",
  "Settings.webhooks.trigger.pending": "In attesa…",
  "Settings.webhooks.trigger.save": "Salva per attivare",
  "Settings.webhooks.trigger.success": "Successo!",
  "Settings.webhooks.trigger.success.label": "Attivazione riuscita",
  "Settings.webhooks.trigger.test": "Test-attivazione",
  "Settings.webhooks.trigger.title": "Salva prima di Attivare",
  "Settings.webhooks.value": "Valore",
  "Settings.webhooks.validation.name.required": "Il nome è obbligatorio",
  "Settings.webhooks.validation.name.regex": "Il nome deve iniziare con una lettera e contenere solo lettere, numeri, spazi e trattini bassi",
  "Settings.webhooks.validation.url.required": "L'URL è obbligatorio",
  "Settings.webhooks.validation.url.regex": "Il valore deve essere un URL valido",
  "Settings.webhooks.validation.key": "La chiave è obbligatoria",
  "Settings.webhooks.validation.value": "Il valore è obbligatorio",
  "Settings.page.PurchaseAudit-logs.description": "Traccia e rivedi le modifiche con il tuo team",
  "Settings.page.PurchaseAudit-logs.perks1": "Traccia facilmente le modifiche",
  "Settings.page.PurchaseAudit-logs.perks2": "Rivedi le modifiche con facilità",
  "Settings.page.PurchaseAudit-logs.perks3": "Mantieni sicurezza e conformità",
  "Settings.page.PurchaseContent-history.description": "Ripristina istantaneamente le modifiche ai contenuti",
  "Settings.page.PurchaseContent-history.perks1": "Sfoglia la cronologia dei tuoi contenuti",
  "Settings.page.PurchaseContent-history.perks2": "Ripristina le modifiche con un clic",
  "Settings.page.PurchaseContent-history.perks3": "Traccia le modifiche tra le diverse lingue",
  "Settings.page.PurchaseSSO.description": "Semplifica l'autenticazione per il tuo team",
  "Settings.page.PurchaseSSO.perks1": "Autenticazione unificata",
  "Settings.page.PurchaseSSO.perks2": "Sicurezza migliorata",
  "Settings.page.PurchaseSSO.perks3": "Supporto per webhook",
  "Settings.page.purchase.upgrade.cta": "Aggiorna",
  "Settings.page.purchase.learn-more.cta": "Scopri di più",
  "Usecase.back-end": "Sviluppatore back-end",
  "Usecase.button.skip": "Salta questa domanda",
  "Usecase.content-creator": "Creatore di contenuti",
  "Usecase.front-end": "Sviluppatore front-end",
  "Usecase.full-stack": "Sviluppatore full-stack",
  "Usecase.input.work-type": "Che tipo di lavoro fai?",
  "Usecase.notification.success.project-created": "Il progetto è stato creato con successo",
  "Usecase.other": "Altro",
  "Usecase.title": "Raccontaci un po' di più su di te",
  "Username": "Nome utente",
  "Users & Permissions": "Utenti & Permessi",
  "Users": "Utenti",
  "Users.components.List.empty": "Non ci sono utenti...",
  "Users.components.List.empty.withFilters": "Non ci sono utenti con i filtri applicati...",
  "Users.components.List.empty.withSearch": "Non ci sono utenti corrispondenti alla ricerca ({search})...",
  "admin.pages.MarketPlacePage.sort.label": "Ordina per",
  "admin.pages.MarketPlacePage.filters.categories": "Categorie",
  "admin.pages.MarketPlacePage.filters.categoriesSelected": "{count, plural, =0 {Nessuna categoria} one {# categoria} other {# categorie}} selezionate",
  "admin.pages.MarketPlacePage.filters.collections": "Collezioni",
  "admin.pages.MarketPlacePage.filters.collectionsSelected": "{count, plural, =0 {Nessuna Collezione} one {# Collezione} other {# Collezioni}} selezionate",
  "admin.pages.MarketPlacePage.head": "Marketplace — Plugin",
  "admin.pages.MarketPlacePage.missingPlugin.description": "Dicci quale plugin stai cercando e lo faremo sapere ai nostri sviluppatori di plugin della community nel caso siano in cerca di ispirazione!",
  "admin.pages.MarketPlacePage.missingPlugin.title": "Ti manca un plugin?",
  "admin.pages.MarketPlacePage.offline.subtitle": "Devi essere connesso a Internet per accedere al Marketplace di Strapi.",
  "admin.pages.MarketPlacePage.offline.title": "Sei offline",
  "admin.pages.MarketPlacePage.plugin.copy": "Copia comando di installazione",
  "admin.pages.MarketPlacePage.plugin.copy.success": "Comando di installazione pronto per essere incollato nel tuo terminale",
  "admin.pages.MarketPlacePage.plugin.downloads": "Questo plugin ha {downloadsCount} download settimanali",
  "admin.pages.MarketPlacePage.plugin.githubStars": "Questo plugin ha ricevuto {starsCount} stelle su GitHub",
  "admin.pages.MarketPlacePage.plugin.info": "Scopri di più",
  "admin.pages.MarketPlacePage.plugin.info.label": "Scopri di più su {pluginName}",
  "admin.pages.MarketPlacePage.plugin.info.text": "Altro",
  "admin.pages.MarketPlacePage.plugin.installed": "Installato",
  "admin.pages.MarketPlacePage.plugin.tooltip.madeByStrapi": "Realizzato da Strapi",
  "admin.pages.MarketPlacePage.plugin.tooltip.verified": "Plugin verificato da Strapi",
  "admin.pages.MarketPlacePage.plugin.version": "Aggiorna la tua versione di Strapi: \"{strapiAppVersion}\" a: \"{versionRange}\"",
  "admin.pages.MarketPlacePage.plugin.version.null": "Impossibile verificare la compatibilità con la tua versione di Strapi: \"{strapiAppVersion}\"",
  "admin.pages.MarketPlacePage.plugins": "Plugin",
  "admin.pages.MarketPlacePage.provider.downloads": "Questo provider ha {downloadsCount} download settimanali",
  "admin.pages.MarketPlacePage.provider.githubStars": "Questo provider ha ricevuto {starsCount} stelle su GitHub",
  "admin.pages.MarketPlacePage.providers": "Provider",
  "admin.pages.MarketPlacePage.search.clear": "Cancella la ricerca",
  "admin.pages.MarketPlacePage.search.empty": "Nessun risultato per \"{target}\"",
  "admin.pages.MarketPlacePage.search.placeholder": "Cerca",
  "admin.pages.MarketPlacePage.sort.alphabetical": "Ordine alfabetico",
  "admin.pages.MarketPlacePage.sort.alphabetical.selected": "Ordina per ordine alfabetico",
  "admin.pages.MarketPlacePage.sort.githubStars": "Numero di stelle GitHub",
  "admin.pages.MarketPlacePage.sort.githubStars.selected": "Ordina per stelle GitHub",
  "admin.pages.MarketPlacePage.sort.newest": "Più recenti",
  "admin.pages.MarketPlacePage.sort.newest.selected": "Ordina per più recenti",
  "admin.pages.MarketPlacePage.sort.npmDownloads": "Numero di download",
  "admin.pages.MarketPlacePage.sort.npmDownloads.selected": "Ordina per download npm",
  "admin.pages.MarketPlacePage.submit.plugin.link": "Invia plugin",
  "admin.pages.MarketPlacePage.submit.provider.link": "Invia provider",
  "admin.pages.MarketPlacePage.subtitle": "Ottieni di più da Strapi",
  "admin.pages.MarketPlacePage.tab-group.label": "Plugin e Provider per Strapi",
  "anErrorOccurred": "Si è verificato un errore",
  "noPreview": "Nessuna anteprima",
  "app.component.CopyToClipboard.label": "Copia negli appunti",
  "app.component.search.label": "Cerca {target}",
  "app.component.table.duplicate": "Duplica {target}",
  "app.component.table.edit": "Modifica {target}",
  "app.component.table.read": "Leggi {target}",
  "app.component.table.select.one-entry": "Seleziona {target}",
  "app.component.table.view": "Dettagli di {target}",
  "app.components.BlockLink.blog": "Blog",
  "app.components.BlockLink.blog.content": "Leggi le ultime notizie su Strapi e l'ecosistema.",
  "app.components.BlockLink.cloud": "Strapi Cloud",
  "app.components.BlockLink.cloud.content": "Hosting cloud completamente gestito per il tuo progetto Strapi.",
  "app.components.BlockLink.code": "Esempi di codice",
  "app.components.BlockLink.code.content": "Impara testando progetti reali sviluppati dalla community.",
  "app.components.BlockLink.documentation.content": "Scopri i concetti essenziali, guide e istruzioni.",
  "app.components.BlockLink.tutorial": "Tutorial",
  "app.components.BlockLink.tutorial.content": "Segui istruzioni passo-passo per utilizzare e personalizzare Strapi.",
  "app.components.Button.cancel": "Annulla",
  "app.components.Button.confirm": "Conferma",
  "app.components.Button.reset": "Reimposta",
  "app.components.ComingSoonPage.comingSoon": "In arrivo",
  "app.components.ConfirmDialog.title": "Conferma",
  "app.components.DownloadInfo.download": "Download in corso...",
  "app.components.DownloadInfo.text": "Potrebbe volerci un minuto. Grazie per la pazienza.",
  "app.components.EmptyAttributes.title": "Non ci sono ancora campi",
  "app.components.EmptyStateLayout.content-document": "Nessun contenuto trovato",
  "app.components.EmptyStateLayout.content-permissions": "Non hai i permessi per accedere a quel contenuto",
  "app.components.GuidedTour.CM.create.content": "<p>Crea e gestisci tutti i contenuti qui nel Content Manager.</p><p>Es: Prendendo l'esempio del sito web del Blog, si può scrivere un Articolo, salvarlo e pubblicarlo come si desidera.</p><p>💡 Consiglio rapido — Non dimenticare di pubblicare i contenuti che crei.</p>",
  "app.components.GuidedTour.CM.create.title": "⚡️ Crea contenuti",
  "app.components.GuidedTour.CM.success.content": "<p>Fantastico, un ultimo passo da fare!</p><b>🚀 Vedi i contenuti in azione</b>",
  "app.components.GuidedTour.CM.success.cta.title": "Testa l'API",
  "app.components.GuidedTour.CM.success.title": "Passo 2: Completato ✅",
  "app.components.GuidedTour.CTB.create.content": "<p>I Tipi di Collezione aiutano a gestire più voci, i Tipi Singoli sono adatti per gestire una sola voce.</p> <p>Es: Per un sito web di Blog, gli Articoli sarebbero un Tipo di Collezione mentre una Homepage sarebbe un Tipo Singolo.</p>",
  "app.components.GuidedTour.CTB.create.cta.title": "Costruisci un Tipo di Collezione",
  "app.components.GuidedTour.CTB.create.title": "🧠 Crea un primo Tipo di Collezione",
  "app.components.GuidedTour.CTB.success.content": "<p>Ottimo lavoro!</p><b>⚡️ Cosa vorresti condividere con il mondo?</b>",
  "app.components.GuidedTour.CTB.success.title": "Passo 1: Completato ✅",
  "app.components.GuidedTour.apiTokens.create.content": "<p>Genera un token di autenticazione qui e recupera il contenuto che hai appena creato.</p>",
  "app.components.GuidedTour.apiTokens.create.cta.title": "Genera un Token API",
  "app.components.GuidedTour.apiTokens.create.title": "🚀 Vedi i contenuti in azione",
  "app.components.GuidedTour.apiTokens.success.content": "<p>Vedi i contenuti in azione facendo una richiesta HTTP:</p><ul><li><p>A questo URL: <light>https://'<'TUO_DOMINIO'>'/api/'<'TUO_CT'>'</light></p></li><li><p>Con l'intestazione: <light>Authorization: bearer '<'TUO_TOKEN_API'>'</light></p></li></ul><p>Per altri modi di interagire con i contenuti, vedi la <documentationLink>documentazione</documentationLink>.</p>",
  "app.components.GuidedTour.apiTokens.success.cta.title": "Torna alla homepage",
  "app.components.GuidedTour.apiTokens.success.title": "Passo 3: Completato ✅",
  "app.components.GuidedTour.create-content": "Crea contenuti",
  "app.components.GuidedTour.home.CM.title": "⚡️ Cosa vorresti condividere con il mondo?",
  "app.components.GuidedTour.home.CTB.cta.title": "Vai al Content Type Builder",
  "app.components.GuidedTour.home.CTB.title": "🧠 Costruisci la struttura dei contenuti",
  "app.components.GuidedTour.home.apiTokens.cta.title": "Testa l'API",
  "app.components.GuidedTour.skip": "Salta il tour",
  "app.components.GuidedTour.title": "3 passi per iniziare",
  "app.components.ImgPreview.hint": "Trascina e rilascia il tuo file in quest'area o {browse} per un file da caricare",
  "app.components.ImgPreview.hint.browse": "sfoglia",
  "app.components.InputFile.newFile": "Aggiungi nuovo file",
  "app.components.InputFileDetails.open": "Apri in una nuova scheda",
  "app.components.InputFileDetails.originalName": "Nome originale:",
  "app.components.InputFileDetails.remove": "Rimuovi questo file",
  "app.components.InputFileDetails.size": "Dimensione:",
  "app.components.InstallPluginPage.Download.description": "Potrebbe volerci qualche secondo per scaricare e installare il plugin.",
  "app.components.InstallPluginPage.Download.title": "Download in corso...",
  "app.components.InstallPluginPage.description": "Estendi la tua app senza sforzo.",
  "app.components.LeftMenu.collapse": "Comprimi la barra di navigazione",
  "app.components.LeftMenu.expand": "Espandi la barra di navigazione",
  "app.components.LeftMenu.general": "Generale",
  "app.components.LeftMenu.logo.alt": "Logo dell'applicazione",
  "app.components.LeftMenu.logout": "Esci",
  "app.components.LeftMenu.navbrand.title": "Dashboard Strapi",
  "app.components.LeftMenu.navbrand.workplace": "Area di lavoro",
  "app.components.LeftMenu.plugins": "Plugin",
  "app.components.LeftMenuFooter.help": "Aiuto",
  "app.components.LeftMenuFooter.poweredBy": "Powered by ",
  "app.components.LeftMenuLinkContainer.collectionTypes": "Tipi di Collezione",
  "app.components.LeftMenuLinkContainer.configuration": "Configurazioni",
  "app.components.LeftMenuLinkContainer.general": "Generale",
  "app.components.LeftMenuLinkContainer.noPluginsInstalled": "Nessun plugin installato ancora",
  "app.components.LeftMenuLinkContainer.plugins": "Plugin",
  "app.components.LeftMenuLinkContainer.singleTypes": "Tipi Singoli",
  "app.components.ListPluginsPage.deletePlugin.description": "Potrebbe volerci qualche secondo per disinstallare il plugin.",
  "app.components.ListPluginsPage.deletePlugin.title": "Disinstallazione",
  "app.components.ListPluginsPage.description": "Elenco dei plugin installati nel progetto.",
  "app.components.ListPluginsPage.head.title": "Elenco plugin",
  "app.components.Logout.logout": "Esci",
  "app.components.Logout.profile": "Profilo",
  "app.components.MarketplaceBanner": "Scopri plugin creati dalla community e molte altre cose fantastiche per avviare il tuo progetto, sul Marketplace di Strapi.",
  "app.components.MarketplaceBanner.image.alt": "Un logo a razzo di Strapi",
  "app.components.MarketplaceBanner.link": "Dai un'occhiata ora",
  "app.components.NotFoundPage.back": "Torna alla homepage",
  "app.components.NotFoundPage.description": "Non trovato",
  "app.components.NpsSurvey.banner-title": "Quanto è probabile che consiglieresti Strapi a un amico o collega?",
  "app.components.NpsSurvey.feedback-response": "Grazie mille per il tuo feedback!",
  "app.components.NpsSurvey.feedback-question": "Hai qualche suggerimento per miglioramenti?",
  "app.components.NpsSurvey.submit-feedback": "Invia Feedback",
  "app.components.NpsSurvey.dismiss-survey-label": "Ignora sondaggio",
  "app.components.NpsSurvey.no-recommendation": "Per niente probabile",
  "app.components.NpsSurvey.happy-to-recommend": "Estremamente probabile",
  "app.components.Official": "Ufficiale",
  "app.components.Onboarding.help.button": "Pulsante di aiuto",
  "app.components.Onboarding.label.completed": "% completato",
  "app.components.Onboarding.link.build-content": "Costruisci un'architettura di contenuti",
  "app.components.Onboarding.link.manage-content": "Aggiungi e gestisci contenuti",
  "app.components.Onboarding.link.manage-media": "Gestisci media",
  "app.components.Onboarding.link.more-videos": "Guarda più video",
  "app.components.Onboarding.title": "Video per Iniziare",
  "app.components.PluginCard.Button.label.download": "Scarica",
  "app.components.PluginCard.Button.label.install": "Già installato",
  "app.components.PluginCard.PopUpWarning.install.impossible.autoReload.needed": "La funzionalità autoReload deve essere abilitata. Avvia la tua app con `yarn develop`.",
  "app.components.PluginCard.PopUpWarning.install.impossible.confirm": "Ho capito!",
  "app.components.PluginCard.PopUpWarning.install.impossible.environment": "Per motivi di sicurezza, un plugin può essere scaricato solo in un ambiente di sviluppo.",
  "app.components.PluginCard.PopUpWarning.install.impossible.title": "Il download è impossibile",
  "app.components.PluginCard.compatible": "Compatibile con la tua app",
  "app.components.PluginCard.compatibleCommunity": "Compatibile con la community",
  "app.components.PluginCard.more-details": "Più dettagli",
  "app.components.ToggleCheckbox.off-label": "Falso",
  "app.components.ToggleCheckbox.on-label": "Vero",
  "app.components.Users.MagicLink.connect": "Copia e condividi questo link per dare accesso a questo utente",
  "app.components.Users.MagicLink.connect.sso": "Invia questo link all'utente, il primo accesso può essere effettuato tramite un provider SSO",
  "app.components.Users.ModalCreateBody.block-title.details": "Dettagli utente",
  "app.components.Users.ModalCreateBody.block-title.roles": "Ruoli dell'utente",
  "app.components.Users.ModalCreateBody.block-title.roles.description": "Un utente può avere uno o più ruoli",
  "app.components.Users.SortPicker.button-label": "Ordina per",
  "app.components.Users.SortPicker.sortby.email_asc": "Email (A-Z)",
  "app.components.Users.SortPicker.sortby.email_desc": "Email (Z-A)",
  "app.components.Users.SortPicker.sortby.firstname_asc": "Nome (A-Z)",
  "app.components.Users.SortPicker.sortby.firstname_desc": "Nome (Z-A)",
  "app.components.Users.SortPicker.sortby.lastname_asc": "Cognome (A-Z)",
  "app.components.Users.SortPicker.sortby.lastname_desc": "Cognome (Z-A)",
  "app.components.Users.SortPicker.sortby.username_asc": "Nome utente (A-Z)",
  "app.components.Users.SortPicker.sortby.username_desc": "Nome utente (Z-A)",
  "app.components.listPlugins.button": "Aggiungi Nuovo Plugin",
  "app.components.listPlugins.title.none": "Nessun plugin installato",
  "app.components.listPluginsPage.deletePlugin.error": "Si è verificato un errore durante la disinstallazione del plugin",
  "app.containers.App.notification.error.init": "Si è verificato un errore durante la richiesta all'API",
  "app.containers.AuthPage.ForgotPasswordSuccess.text.contact-admin": "Se non ricevi questo link, contatta il tuo amministratore.",
  "app.containers.AuthPage.ForgotPasswordSuccess.text.email": "Potrebbero volerci alcuni minuti per ricevere il link di recupero password.",
  "app.containers.AuthPage.ForgotPasswordSuccess.title": "Email inviata",
  "app.containers.Users.EditPage.form.active.label": "Attivo",
  "app.containers.Users.EditPage.header.label": "Modifica {name}",
  "app.containers.Users.EditPage.header.label-loading": "Modifica utente",
  "app.containers.Users.EditPage.roles-bloc-title": "Ruoli attribuiti",
  "app.containers.Users.ModalForm.footer.button-success": "Invita utente",
  "app.links.configure-view": "Configura la vista",
  "app.page.not.found": "Oops! Non riusciamo a trovare la pagina che stai cercando...",
  "app.static.links.cheatsheet": "Cheatsheet",
  "app.utils.SelectOption.defaultMessage": " ",
  "app.utils.add-filter": "Aggiungi filtro",
  "app.utils.close-label": "Chiudi",
  "app.utils.defaultMessage": " ",
  "app.utils.delete": "Elimina",
  "app.utils.duplicate": "Duplica",
  "app.utils.edit": "Modifica",
  "app.utils.errors.file-too-big.message": "Il file è troppo grande",
  "app.utils.filter-value": "Valore del filtro",
  "app.utils.filters": "Filtri",
  "app.utils.notify.data-loaded": "{target} è stato caricato",
  "app.utils.placeholder.defaultMessage": " ",
  "app.utils.publish": "Pubblica",
  "app.utils.refresh": "Aggiorna",
  "app.utils.select-all": "Seleziona tutto",
  "app.utils.select-field": "Seleziona campo",
  "app.utils.select-filter": "Seleziona filtro",
  "app.utils.unpublish": "Annulla pubblicazione",
  "app.utils.published": "Pubblicato",
  "app.utils.ready-to-publish": "Pronto per la pubblicazione",
  "app.utils.already-published": "Già pubblicato",
  "app.utils.ready-to-publish-changes": "Pronto per pubblicare le modifiche",
  "app.utils.ready-to-unpublish-changes": "Pronto per annullare la pubblicazione",
  "app.confirm.body": "Sei sicuro?",
  "clearLabel": "Cancella",
  "coming.soon": "Questo contenuto è attualmente in costruzione e tornerà tra qualche settimana!",
  "component.Input.error.validation.integer": "Il valore deve essere un intero",
  "components.AutoReloadBlocker.description": "Esegui Strapi con uno dei seguenti comandi:",
  "components.AutoReloadBlocker.header": "La funzionalità di ricarica è necessaria per questo plugin.",
  "components.ErrorBoundary.title": "Qualcosa è andato storto...",
  "components.FilterOptions.FILTER_TYPES.$contains": "contiene",
  "components.FilterOptions.FILTER_TYPES.$containsi": "contiene (case insensitive)",
  "components.FilterOptions.FILTER_TYPES.$endsWith": "finisce con",
  "components.FilterOptions.FILTER_TYPES.$endsWithi": "finisce con (case insensitive)",
  "components.FilterOptions.FILTER_TYPES.$eq": "è",
  "components.FilterOptions.FILTER_TYPES.$eqi": "è (case insensitive)",
  "components.FilterOptions.FILTER_TYPES.$gt": "è maggiore di",
  "components.FilterOptions.FILTER_TYPES.$gte": "è maggiore o uguale a",
  "components.FilterOptions.FILTER_TYPES.$lt": "è minore di",
  "components.FilterOptions.FILTER_TYPES.$lte": "è minore o uguale a",
  "components.FilterOptions.FILTER_TYPES.$ne": "non è",
  "components.FilterOptions.FILTER_TYPES.$nei": "non è (case insensitive)",
  "components.FilterOptions.FILTER_TYPES.$notContains": "non contiene",
  "components.FilterOptions.FILTER_TYPES.$notContainsi": "non contiene (case insensitive)",
  "components.FilterOptions.FILTER_TYPES.$notNull": "non è nullo",
  "components.FilterOptions.FILTER_TYPES.$null": "è nullo",
  "components.FilterOptions.FILTER_TYPES.$startsWith": "inizia con",
  "components.FilterOptions.FILTER_TYPES.$startsWithi": "inizia con (case insensitive)",
  "components.Input.error.attribute.key.taken": "Questo valore esiste già",
  "components.Input.error.attribute.sameKeyAndName": "Non può essere uguale",
  "components.Input.error.attribute.taken": "Questo nome di campo esiste già",
  "components.Input.error.contain.lowercase": "La password deve contenere almeno un carattere minuscolo",
  "components.Input.error.contain.number": "La password deve contenere almeno un numero",
  "components.Input.error.contain.maxBytes": "La password deve essere inferiore a 73 byte",
  "components.Input.error.contain.uppercase": "La password deve contenere almeno un carattere maiuscolo",
  "components.Input.error.contentTypeName.taken": "Questo nome esiste già",
  "components.Input.error.custom-error": "{errorMessage} ",
  "components.Input.error.password.noMatch": "Le password non corrispondono",
  "components.Input.error.validation.email": "Questa non è un'email valida",
  "components.Input.error.validation.json": "Questo non corrisponde al formato JSON",
  "components.Input.error.validation.lowercase": "Il valore deve essere una stringa minuscola",
  "components.Input.error.validation.max": "Il valore è troppo alto (max: {max}).",
  "components.Input.error.validation.maxLength": "Il valore è troppo lungo (max: {max}).",
  "components.Input.error.validation.min": "Il valore è troppo basso (min: {min}).",
  "components.Input.error.validation.minLength": "Il valore è troppo corto (min: {min}).",
  "components.Input.error.validation.minSupMax": "Non può essere superiore",
  "components.Input.error.validation.regex": "Il valore non corrisponde al regex.",
  "components.Input.error.validation.string": "Questa non è una stringa valida.",
  "components.Input.error.validation.required": "Questo valore è obbligatorio.",
  "components.Input.error.validation.unique": "Questo valore è già utilizzato.",
  "components.Input.error.validation.email.withField": "{field} non è un'email valida",
  "components.Input.error.validation.json.withField": "{field} non corrisponde al formato JSON",
  "components.Input.error.validation.lowercase.withField": "{field} deve essere una stringa minuscola",
  "components.Input.error.validation.max.withField": "{field} è troppo alto.",
  "components.Input.error.validation.maxLength.withField": "{field} è troppo lungo.",
  "components.Input.error.validation.min.withField": "{field} è troppo basso.",
  "components.Input.error.validation.minLength.withField": "{field} è troppo corto.",
  "components.Input.error.validation.minSupMax.withField": "{field} non può essere superiore",
  "components.Input.error.validation.regex.withField": "{field} non corrisponde al regex.",
  "components.Input.error.validation.required.withField": "{field} è obbligatorio.",
  "components.Input.error.validation.unique.withField": "{field} è già utilizzato.",
  "components.InputSelect.option.placeholder": "Scegli qui",
  "components.ListRow.empty": "Non ci sono dati da mostrare.",
  "components.NotAllowedInput.text": "Nessun permesso per vedere questo campo",
  "components.OverlayBlocker.description": "Stai utilizzando una funzionalità che necessita il riavvio del server. La pagina si ricaricherà automaticamente.",
  "components.OverlayBlocker.description.serverError": "Il server avrebbe dovuto riavviarsi, controlla i tuoi log nel terminale.",
  "components.OverlayBlocker.title": "In attesa del riavvio...",
  "components.OverlayBlocker.title.serverError": "Il riavvio sta richiedendo più tempo del previsto",
  "components.PageFooter.select": "Voci per pagina",
  "components.ProductionBlocker.description": "Per motivi di sicurezza dobbiamo disabilitare questo plugin in altri ambienti.",
  "components.ProductionBlocker.header": "Questo plugin è disponibile solo in modalità sviluppo.",
  "components.ViewSettings.tooltip": "Impostazioni di visualizzazione",
  "components.TableHeader.sort": "Ordina per {label}",
  "components.Blocks.modifiers.bold": "Grassetto",
  "components.Blocks.modifiers.italic": "Corsivo",
  "components.Blocks.modifiers.underline": "Sottolineato",
  "components.Blocks.modifiers.strikethrough": "Barrato",
  "components.Blocks.modifiers.code": "Codice inline",
  "components.Blocks.link": "Link",
  "components.Blocks.expand": "Espandi",
  "components.Blocks.collapse": "Comprimi",
  "components.Blocks.popover.text": "Testo",
  "components.Blocks.popover.text.placeholder": "Inserisci il testo del link",
  "components.Blocks.popover.link": "Link",
  "components.Blocks.popover.link.placeholder": "Incolla il link",
  "components.Blocks.popover.link.error": "Inserisci un link valido",
  "components.Blocks.popover.remove": "Rimuovi",
  "components.Blocks.popover.edit": "Modifica",
  "components.Blocks.blocks.selectBlock": "Seleziona un blocco",
  "components.Blocks.blocks.text": "Testo",
  "components.Blocks.blocks.heading1": "Titolo 1",
  "components.Blocks.blocks.heading2": "Titolo 2",
  "components.Blocks.blocks.heading3": "Titolo 3",
  "components.Blocks.blocks.heading4": "Titolo 4",
  "components.Blocks.blocks.heading5": "Titolo 5",
  "components.Blocks.blocks.heading6": "Titolo 6",
  "components.Blocks.blocks.code": "Blocco di codice",
  "components.Blocks.blocks.quote": "Citazione",
  "components.Blocks.blocks.image": "Immagine",
  "components.Blocks.blocks.unorderedList": "Elenco puntato",
  "components.Blocks.blocks.orderedList": "Elenco numerato",
  "components.Blocks.blocks.code.languageLabel": "Seleziona una lingua",
  "components.Blocks.dnd.instruction": "Per riordinare i blocchi, premi Command o Control insieme a Shift e i tasti freccia Su o Giù",
  "components.Blocks.dnd.reorder": "{item}, spostato. Nuova posizione nell'editor: {position}.",
  "components.Wysiwyg.ToggleMode.markdown-mode": "Modalità Markdown",
  "components.Wysiwyg.ToggleMode.preview-mode": "Modalità anteprima",
  "components.Wysiwyg.collapse": "Comprimi",
  "components.Wysiwyg.blocks.code": "Codice",
  "components.Wysiwyg.selectOptions.H1": "Titolo 1",
  "components.Wysiwyg.selectOptions.H2": "Titolo 2",
  "components.Wysiwyg.selectOptions.H3": "Titolo 3",
  "components.Wysiwyg.selectOptions.H4": "Titolo 4",
  "components.Wysiwyg.selectOptions.H5": "Titolo 5",
  "components.Wysiwyg.selectOptions.H6": "Titolo 6",
  "components.Wysiwyg.selectOptions.title": "Titoli",
  "components.WysiwygBottomControls.charactersIndicators": "caratteri",
  "components.WysiwygBottomControls.fullscreen": "Espandi",
  "components.WysiwygBottomControls.uploadFiles": "Trascina e rilascia file, incolla dagli appunti o {browse}.",
  "components.WysiwygBottomControls.uploadFiles.browse": "selezionali",
  "components.pagination.go-to": "Vai alla pagina {page}",
  "components.pagination.go-to-next": "Vai alla pagina successiva",
  "components.pagination.go-to-previous": "Vai alla pagina precedente",
  "components.pagination.remaining-links": "E altri {number} link",
  "components.popUpWarning.button.cancel": "No, annulla",
  "components.popUpWarning.button.confirm": "Sì, conferma",
  "components.popUpWarning.message": "Sei sicuro di voler eliminare questo?",
  "components.popUpWarning.title": "Per favore conferma",
  "dark": "scuro",
  "form.button.continue": "Continua",
  "form.button.done": "Fatto",
  "global.actions": "Azioni",
  "global.auditLogs": "Log di Audit",
  "global.back": "Indietro",
  "global.cancel": "Annulla",
  "global.change-password": "Cambia password",
  "global.close": "Chiudi",
  "global.content-manager": "Gestore dei Contenuti",
  "global.home": "Home",
  "global.continue": "Continua",
  "global.delete": "Elimina",
  "global.delete-target": "Elimina {target}",
  "global.description": "Descrizione",
  "global.details": "Dettagli",
  "global.disabled": "Disabilitato",
  "global.documentation": "Documentazione",
  "global.enabled": "Abilitato",
  "global.error": "Si è verificato un errore",
  "global.finish": "Termina",
  "global.marketplace": "Marketplace",
  "global.more": "Altro",
  "global.name": "Nome",
  "global.new": "Nuovo",
  "global.none": "Nessuno",
  "global.password": "Password",
  "global.plugins": "Plugin",
  "global.plugins.content-manager": "Gestore dei Contenuti",
  "global.plugins.content-manager.description": "Modo rapido per vedere, modificare ed eliminare i dati nel tuo database.",
  "global.plugins.content-type-builder": "Costruttore di Tipi di Contenuto",
  "global.plugins.content-type-builder.description": "Modella la struttura dei dati della tua API. Crea nuovi campi e relazioni in pochi minuti. I file vengono creati e aggiornati automaticamente nel tuo progetto.",
  "global.plugins.documentation": "Documentazione",
  "global.plugins.documentation.description": "Crea un documento OpenAPI e visualizza la tua API con SWAGGER UI.",
  "global.plugins.email": "Email",
  "global.plugins.email.description": "Configura la tua applicazione per inviare email.",
  "global.plugins.graphql": "GraphQL",
  "global.plugins.graphql.description": "Aggiunge un endpoint GraphQL con metodi API predefiniti.",
  "global.plugins.i18n": "Internazionalizzazione",
  "global.plugins.i18n.description": "Questo plugin permette di creare, leggere e aggiornare contenuti in lingue diverse, sia dal Pannello di Amministrazione che dall'API.",
  "global.plugins.sentry": "Sentry",
  "global.plugins.sentry.description": "Invia eventi di errore Strapi a Sentry.",
  "global.plugins.upload": "Libreria Multimediale",
  "global.plugins.upload.description": "Gestione dei file multimediali.",
  "global.plugins.users-permissions": "Ruoli & Permessi",
  "global.plugins.users-permissions.description": "Proteggi la tua API con un processo di autenticazione completo basato su JWT. Questo plugin viene anche fornito con una strategia ACL che ti permette di gestire i permessi tra i gruppi di utenti.",
  "global.profile": "Impostazioni profilo",
  "global.prompt.unsaved": "Sei sicuro di voler lasciare questa pagina? Tutte le tue modifiche andranno perse",
  "global.reset-password": "Reimposta password",
  "global.roles": "Ruoli",
  "global.save": "Salva",
  "global.search": "Cerca",
  "global.see-more": "Vedi altro",
  "global.select": "Seleziona",
  "global.select-all-entries": "Seleziona tutte le voci",
  "global.settings": "Impostazioni",
  "global.type": "Tipo",
  "global.users": "Utenti",
  "global.fullname": "{firstname} {lastname}",
  "global.learn-more": "Scopri di più",
  "light": "chiaro",
  "notification.contentType.relations.conflict": "Il tipo di contenuto ha relazioni in conflitto",
  "notification.default.title": "Informazione:",
  "notification.ee.warning.at-seat-limit.title": "{licenseLimitStatus, select, OVER_LIMIT {Oltre} AT_LIMIT {Al}} limite di posti ({currentUserCount}/{permittedSeats})",
  "notification.ee.warning.over-.message": "Aggiungi posti per {licenseLimitStatus, select, OVER_LIMIT {invitare} AT_LIMIT {riabilitare}} Utenti. Se l'hai già fatto ma non si riflette ancora in Strapi, assicurati di riavviare la tua app.",
  "notification.error": "Si è verificato un errore",
  "notification.error.invalid.configuration": "Hai una configurazione non valida, controlla il log del tuo server per maggiori informazioni.",
  "notification.error.layout": "Impossibile recuperare il layout",
  "notification.error.tokennamenotunique": "Nome già assegnato a un altro token",
  "notification.form.error.fields": "Il modulo contiene alcuni errori",
  "notification.form.success.fields": "Modifiche salvate",
  "notification.link-copied": "Link copiato negli appunti",
  "notification.permission.not-allowed-read": "Non hai il permesso di vedere questo documento",
  "notification.success.apitokencreated": "Token API creato con successo",
  "notification.success.apitokenedited": "Token API modificato con successo",
  "notification.success.delete": "L'elemento è stato eliminato",
  "notification.success.saved": "Salvato",
  "notification.success.title": "Successo:",
  "notification.success.transfertokencreated": "Token di Trasferimento creato con successo",
  "notification.success.transfertokenedited": "Token di Trasferimento modificato con successo",
  "notification.version.update.message": "È disponibile una nuova versione di Strapi!",
  "notification.warning.404": "404 - Non trovato",
  "notification.warning.title": "Attenzione:",
  "or": "o",
  "request.error.model.unknown": "Questo modello non esiste",
  "selectButtonTitle": "Seleziona",
  "skipToContent": "Vai al contenuto",
  "submit": "Invia",
  "App.schemas.data-loaded": "Gli schemi sono stati caricati con successo",
  "actions.clone.error": "Si è verificato un errore durante il tentativo di clonare il documento.",
  "actions.clone.label": "Duplica",
  "actions.delete.dialog.body": "Sei sicuro di voler eliminare questo documento? Questa azione è irreversibile.",
  "actions.delete.error": "Si è verificato un errore durante il tentativo di eliminare il documento.",
  "actions.delete.label": "Elimina voce{isLocalized, select, true { (tutte le lingue)} other {}}",
  "actions.discard.label": "Scarta modifiche",
  "actions.discard.dialog.body": "Sei sicuro di voler scartare le modifiche? Questa azione è irreversibile.",
  "actions.edit.error": "Si è verificato un errore durante il tentativo di modificare il documento.",
  "actions.edit.label": "Modifica",
  "actions.unpublish.error": "Si è verificato un errore durante il tentativo di annullare la pubblicazione del documento.",
  "actions.unpublish.dialog.body": "Sei sicuro di voler annullare la pubblicazione di questo?",
  "actions.unpublish.dialog.option.keep-draft": "Annulla pubblicazione e mantieni l'ultima bozza",
  "actions.unpublish.dialog.option.replace-draft": "Annulla pubblicazione e sostituisci l'ultima bozza",
  "ListViewTable.relation-loaded": "Le relazioni sono state caricate",
  "ListViewTable.relation-loading": "Le relazioni si stanno caricando",
  "ListViewTable.relation-more": "Questa relazione contiene più entità di quelle visualizzate",
  "EditRelations.title": "Dati relazionali",
  "HeaderLayout.button.label-add-entry": "Crea nuova voce",
  "content-manager.HeaderLayout.button.label-add-entry": "Crea nuova voce",
  "api.id": "ID API",
  "apiError.This attribute must be unique": "{field} deve essere unico",
  "components.AddFilterCTA.add": "Filtri",
  "components.AddFilterCTA.hide": "Filtri",
  "components.DragHandle-label": "Trascina",
  "components.DraggableAttr.edit": "Clicca per modificare",
  "components.DraggableCard.delete.field": "Elimina {item}",
  "components.DraggableCard.edit.field": "Modifica {item}",
  "components.DraggableCard.move.field": "Sposta {item}",
  "components.ListViewTable.row-line": "riga elemento {number}",
  "components.DynamicZone.ComponentPicker-label": "Scegli un componente",
  "components.DynamicZone.add-component": "Aggiungi un componente a {componentName}",
  "components.DynamicZone.delete-label": "Elimina {name}",
  "components.DynamicZone.error-message": "Il componente contiene errori",
  "components.DynamicZone.missing-components": "Ci {number, plural, =0 {sono # componenti mancanti} one {è # componente mancante} other {sono # componenti mancanti}}",
  "components.DynamicZone.extra-components": "Ci {number, plural, =0 {sono # componenti extra} one {è # componente extra} other {sono # componenti extra}}",
  "components.DynamicZone.move-down-label": "Sposta componente in basso",
  "components.DynamicZone.move-up-label": "Sposta componente in alto",
  "components.DynamicZone.pick-compo": "Scegli un componente",
  "components.DynamicZone.required": "Il componente è obbligatorio",
  "components.EmptyAttributesBlock.button": "Vai alla pagina delle impostazioni",
  "components.EmptyAttributesBlock.description": "Puoi modificare le tue impostazioni",
  "components.FieldItem.linkToComponentLayout": "Imposta il layout del componente",
  "components.FieldSelect.label": "Aggiungi un campo",
  "components.FilterOptions.button.apply": "Applica",
  "components.FiltersPickWrapper.PluginHeader.actions.apply": "Applica",
  "components.FiltersPickWrapper.PluginHeader.actions.clearAll": "Cancella tutto",
  "components.FiltersPickWrapper.PluginHeader.description": "Imposta le condizioni da applicare per filtrare le voci",
  "components.FiltersPickWrapper.PluginHeader.title.filter": "Filtri",
  "components.FiltersPickWrapper.hide": "Nascondi",
  "components.Filters.usersSelect.label": "Cerca e seleziona un utente per filtrare",
  "components.LeftMenu.Search.label": "Cerca un tipo di contenuto",
  "components.LeftMenu.collection-types": "Tipi di Collezione",
  "components.LeftMenu.single-types": "Tipi Singoli",
  "components.LimitSelect.itemsPerPage": "Elementi per pagina",
  "components.RelationInput.icon-button-aria-label": "Trascina",
  "components.RelationInputModal.modal-title": "Modifica una relazione",
  "components.RelationInputModal.button-fullpage": "Vai alla voce",
  "components.RelationInputModal.confirmation-message": "Alcune modifiche non sono state salvate. Sei sicuro di voler chiudere questa relazione? Tutte le modifiche non salvate andranno perse.",
  "components.RepeatableComponent.error-message": "Il/I componente/i contiene/contengono errori",
  "components.Search.placeholder": "Cerca una voce...",
  "components.Select.draft-info-title": "Bozza",
  "components.Select.publish-info-title": "Pubblicato",
  "components.SettingsViewWrapper.pluginHeader.description.edit-settings": "Personalizza come apparirà la vista di modifica.",
  "components.SettingsViewWrapper.pluginHeader.description.list-settings": "Definisci le impostazioni della vista elenco.",
  "components.SettingsViewWrapper.pluginHeader.title": "Configura la vista — {name}",
  "bulk-publish.already-published": "Già Pubblicato",
  "bulk-unpublish.already-unpublished": "Già Non Pubblicato",
  "bulk-publish.modified": "Pronto per pubblicare le modifiche",
  "bulk-publish.waiting-for-action": "In attesa di azione",
  "components.TableDelete.delete": "Elimina tutto",
  "components.TableDelete.deleteSelected": "Elimina selezionati",
  "components.TableDelete.label": "{number, plural, one {# voce} other {# voci}} selezionate",
  "components.TableEmpty.withFilters": "Non ci sono {contentType} con i filtri applicati…",
  "components.TableEmpty.withSearch": "Non ci sono {contentType} corrispondenti alla ricerca ({search})…",
  "components.TableEmpty.withoutFilter": "Non ci sono {contentType}…",
  "components.empty-repeatable": "Nessuna voce ancora. Clicca per aggiungerne una.",
  "components.notification.info.maximum-requirement": "Hai già raggiunto il numero massimo di campi",
  "components.notification.info.minimum-requirement": "È stato aggiunto un campo per soddisfare il requisito minimo",
  "components.repeatable.reorder.error": "Si è verificato un errore durante il riordinamento del campo del tuo componente, riprova",
  "components.reset-entry": "Reimposta voce",
  "components.uid.apply": "applica",
  "components.uid.available": "Disponibile",
  "components.uid.regenerate": "Rigenera",
  "components.uid.suggested": "suggerito",
  "components.uid.unavailable": "Non disponibile",
  "containers.edit.tabs.label": "Stato del documento",
  "containers.edit.tabs.draft": "bozza",
  "containers.edit.tabs.published": "pubblicato",
  "containers.edit.panels.default.title": "Voce",
  "containers.edit.panels.default.more-actions": "Altre azioni del documento",
  "containers.Edit.delete": "Elimina",
  "containers.edit.title.new": "Crea una voce",
  "containers.edit.header.more-actions": "Altre azioni",
  "containers.edit.information.last-published.label": "Pubblicato",
  "containers.edit.information.last-published.value": "{time}{isAnonymous, select, true {} other { da {author}}}",
  "containers.edit.information.last-draft.label": "Aggiornato",
  "containers.edit.information.last-draft.value": "{time}{isAnonymous, select, true {} other { da {author}}}",
  "containers.edit.information.document.label": "Creato",
  "containers.edit.information.document.value": "{time}{isAnonymous, select, true {} other { da {author}}}",
  "containers.EditSettingsView.modal-form.edit-field": "Modifica il campo",
  "containers.EditView.add.new-entry": "Aggiungi una voce",
  "containers.EditView.notification.errors": "Il modulo contiene alcuni errori",
  "containers.Home.introduction": "Per modificare le tue voci vai al link specifico nel menu di sinistra. Questo plugin non ha un modo appropriato per modificare le impostazioni ed è ancora in fase di sviluppo attivo.",
  "containers.Home.pluginHeaderDescription": "Gestisci le tue voci attraverso un'interfaccia potente e bella.",
  "containers.Home.pluginHeaderTitle": "Gestore dei Contenuti",
  "containers.List.draft": "Bozza",
  "containers.List.published": "Pubblicato",
  "containers.List.modified": "Modificato",
  "containers.list.displayedFields": "Campi Visualizzati",
  "containers.list.items": "{number} {number, plural, =0 {elementi} one {elemento} other {elementi}}",
  "containers.list.table.row-actions": "Azioni riga",
  "containers.list.selectedEntriesModal.title": "Pubblica voci",
  "containers.list.selectedEntriesModal.selectedCount.publish": "{publishedCount} {publishedCount, plural, =0 {voci} one {voce} other {voci}} già pubblicate. {draftCount} {draftCount, plural, =0 {voci} one {voce} other {voci}} pronte per la pubblicazione. {withErrorsCount} {withErrorsCount, plural, =0 {voci} one {voce} other {voci}} in attesa di azione.",
  "containers.list.selectedEntriesModal.selectedCount.unpublish": "{draftCount} {draftCount, plural, =0 {voci} one {voce} other {voci}} già non pubblicate. {publishedCount} {publishedCount, plural, =0 {voci} one {voce} other {voci}} pronte per annullare la pubblicazione.",
  "containers.list.autoCloneModal.header": "Duplica",
  "containers.list.autoCloneModal.title": "Questa voce non può essere duplicata direttamente.",
  "containers.list.autoCloneModal.description": "Verrà creata una nuova voce con lo stesso contenuto, ma dovrai modificare i seguenti campi per salvarla.",
  "containers.list.autoCloneModal.create": "Crea",
  "containers.list.autoCloneModal.error.unique": "Non sono consentiti valori identici in un campo unico.",
  "containers.list.autoCloneModal.error.relation": "La duplicazione della relazione potrebbe rimuoverla dalla voce originale.",
  "containers.list-settings.modal-form.label": "Modifica {fieldName}",
  "containers.list-settings.modal-form.error": "Si è verificato un errore durante il tentativo di aprire il modulo.",
  "containers.edit-settings.modal-form.error": "Si è verificato un errore durante il tentativo di aprire il modulo.",
  "containers.edit-settings.modal-form.label": "Etichetta",
  "containers.edit-settings.modal-form.description": "Descrizione",
  "containers.edit-settings.modal-form.placeholder": "Segnaposto",
  "containers.edit-settings.modal-form.mainField": "Titolo della voce",
  "containers.edit-settings.modal-form.mainField.hint": "Imposta il campo visualizzato sia nella vista di modifica che in quella di elenco",
  "containers.edit-settings.modal-form.editable": "Campo modificabile",
  "containers.edit-settings.modal-form.size": "Dimensione",
  "containers.SettingPage.add.field": "Inserisci un altro campo",
  "containers.SettingPage.add.relational-field": "Inserisci un altro campo relazionale",
  "containers.SettingPage.attributes": "Campi degli attributi",
  "containers.SettingPage.attributes.description": "Definisci l'ordine degli attributi",
  "containers.SettingPage.editSettings.description": "Trascina e rilascia i campi per costruire il layout",
  "containers.SettingPage.editSettings.entry.title": "Titolo della voce",
  "containers.SettingPage.editSettings.entry.title.description": "Imposta il campo visualizzato della tua voce",
  "containers.SettingPage.editSettings.relation-field.description": "Imposta il campo visualizzato sia nella vista di modifica che in quella di elenco",
  "containers.SettingPage.editSettings.title": "Vista di modifica (impostazioni)",
  "containers.SettingPage.layout": "Layout",
  "containers.SettingPage.listSettings.description": "Configura le opzioni per questo Tipo di Collezione",
  "containers.SettingPage.listSettings.title": "Vista elenco (impostazioni)",
  "containers.SettingPage.pluginHeaderDescription": "Configura le impostazioni specifiche per questo Tipo di Collezione",
  "containers.SettingPage.relations": "Campi relazionali",
  "containers.SettingPage.settings": "Impostazioni",
  "containers.SettingPage.view": "Vista",
  "containers.SettingViewModel.pluginHeader.title": "Gestore dei Contenuti — {name}",
  "containers.SettingsPage.Block.contentType.description": "Configura le impostazioni specifiche",
  "containers.SettingsPage.Block.contentType.title": "Tipi di Collezione",
  "containers.SettingsPage.Block.generalSettings.description": "Configura le opzioni predefinite per i tuoi Tipi di Collezione",
  "containers.SettingsPage.Block.generalSettings.title": "Generale",
  "containers.SettingsPage.pluginHeaderDescription": "Configura le impostazioni per tutti i tuoi Tipi di Collezione e Gruppi",
  "containers.SettingsView.list.subtitle": "Configura il layout e la visualizzazione dei tuoi Tipi di Collezione e Gruppi",
  "containers.SettingsView.list.title": "Configurazioni di visualizzazione",
  "containers.untitled": "Senza titolo",
  "dnd.cancel-item": "{item}, rilasciato. Riordinamento annullato.",
  "dnd.drop-item": "{item}, rilasciato. Posizione finale nell'elenco: {position}.",
  "dnd.grab-item": "{item}, afferrato. Posizione attuale nell'elenco: {position}. Premi le frecce su e giù per cambiare posizione, Spazio per rilasciare, Esc per annullare.",
  "dnd.instructions": "Premi la barra spaziatrice per afferrare e riordinare",
  "dnd.reorder": "{item}, spostato. Nuova posizione nell'elenco: {position}.",
  "edit-settings-view.link-to-ctb.components": "Modifica il componente",
  "edit-settings-view.link-to-ctb.content-types": "Modifica il tipo di contenuto",
  "emptyAttributes.button": "Vai al Costruttore di Tipi di Collezione",
  "emptyAttributes.description": "Aggiungi il tuo primo campo al Tipo di Collezione",
  "emptyAttributes.title": "Non ci sono ancora campi",
  "error.attribute.key.taken": "Questo valore esiste già",
  "error.attribute.sameKeyAndName": "Non possono essere uguali",
  "error.attribute.taken": "Questo nome di campo esiste già",
  "error.contentTypeName.taken": "Questo nome esiste già",
  "error.model.fetch": "Si è verificato un errore durante il recupero della configurazione dei modelli.",
  "error.record.create": "Si è verificato un errore durante la creazione del record.",
  "error.record.delete": "Si è verificato un errore durante l'eliminazione del record.",
  "error.record.fetch": "Si è verificato un errore durante il recupero del record.",
  "error.record.update": "Si è verificato un errore durante l'aggiornamento del record.",
  "error.records.count": "Si è verificato un errore durante il conteggio dei record.",
  "error.records.fetch": "Si è verificato un errore durante il recupero dei record.",
  "error.records.fetch-draft-relatons": "Si è verificato un errore durante il recupero delle relazioni bozza su questo documento.",
  "error.schema.generation": "Si è verificato un errore durante la generazione dello schema.",
  "error.validation.json": "Questo non è un JSON",
  "error.validation.max": "Il valore è troppo alto (max: {max}).",
  "error.validation.maxLength": "Il valore è troppo lungo (max: {max}).",
  "error.validation.min": "Il valore è troppo basso (min: {min}).",
  "error.validation.minLength": "Il valore è troppo corto (min: {min}).",
  "error.validation.minSupMax": "Non può essere superiore",
  "error.validation.regex": "Il valore non corrisponde al regex.",
  "error.validation.required": "Questo valore di input è richiesto.",
  "form.Input.bulkActions": "Abilita azioni di massa",
  "form.Input.defaultSort": "Attributo di ordinamento predefinito",
  "form.Input.description": "Descrizione",
  "form.Input.description.placeholder": "Nome visualizzato nel profilo",
  "form.Input.editable": "Campo modificabile",
  "form.Input.filters": "Abilita filtri",
  "form.Input.hint.character.unit": "{maxValue, plural, one { carattere} other { caratteri}}",
  "form.Input.hint.minMaxDivider": " / ",
  "form.Input.hint.text": "{min, select, undefined {} other {min. {min}}}{divider}{max, select, undefined {} other {max. {max}}}{unit}{br}{description}",
  "form.Input.label": "Etichetta",
  "form.Input.label.inputDescription": "Questo valore sovrascrive l'etichetta visualizzata nell'intestazione della tabella",
  "form.Input.pageEntries": "Voci per pagina",
  "form.Input.pageEntries.inputDescription": "Nota: Puoi sovrascrivere questo valore nella pagina delle impostazioni del Tipo di Collezione.",
  "form.Input.placeholder": "Segnaposto",
  "form.Input.placeholder.placeholder": "Il mio valore fantastico",
  "form.Input.search": "Abilita ricerca",
  "form.Input.search.field": "Abilita ricerca su questo campo",
  "form.Input.sort.field": "Abilita ordinamento su questo campo",
  "form.Input.sort.order": "Ordine di ordinamento predefinito",
  "form.Input.wysiwyg": "Visualizza come WYSIWYG",
  "global.displayedFields": "Campi Visualizzati",
  "groups": "Gruppi",
  "groups.numbered": "Gruppi ({number})",
  "header.name": "Gestore dei Contenuti",
  "link-to-ctb": "Modifica il modello",
  "models": "Tipi di Collezione",
  "models.numbered": "Tipi di Collezione ({number})",
  "notification.error.displayedFields": "È necessario almeno un campo visualizzato",
  "notification.error.relationship.fetch": "Si è verificato un errore durante il recupero della relazione.",
  "notification.info.SettingPage.disableSort": "È necessario avere un attributo con l'ordinamento consentito",
  "notification.info.minimumFields": "È necessario avere almeno un campo visualizzato",
  "notification.upload.error": "Si è verificato un errore durante il caricamento dei tuoi file",
  "pageNotFound": "Pagina non trovata",
  "pages.ListView.header-subtitle": "{number, plural, =0 {# voci} one {# voce} other {# voci}} trovate",
  "pages.NoContentType.button": "Crea il tuo primo Tipo di Contenuto",
  "pages.NoContentType.text": "Non hai ancora nessun contenuto, ti consigliamo di creare il tuo primo Tipo di Contenuto.",
  "permissions.not-allowed.create": "Non sei autorizzato a creare un documento",
  "permissions.not-allowed.update": "Non sei autorizzato a vedere questo documento",
  "plugin.description.long": "Modo rapido per vedere, modificare ed eliminare i dati nel tuo database.",
  "plugin.description.short": "Modo rapido per vedere, modificare ed eliminare i dati nel tuo database.",
  "popUpWarning.bodyMessage.contentType.delete": "Sei sicuro di voler eliminare il Tipo di Contenuto?",
  "popUpWarning.bodyMessage.contentType.delete.all": "Sei sicuro di voler eliminare queste voci?",
  "popUpWarning.bodyMessage.contentType.publish.all": "Sei sicuro di voler pubblicare queste voci?",
  "popUpWarning.bodyMessage.contentType.unpublish.all": "Sei sicuro di voler annullare la pubblicazione di queste voci?",
  "popUpWarning.warning.has-draft-relations.title": "Conferma",
  "popUpWarning.warning.has-draft-relations.message": "Questa voce è correlata a {count, plural, one {# voce bozza} other {# voci bozza}}. Pubblicarla potrebbe lasciare collegamenti interrotti nella tua app.",
  "popUpwarning.warning.has-draft-relations.button-confirm": "Sì, pubblica",
  "popUpwarning.warning.bulk-has-draft-relations.message": "{count} {count, plural, one { relazione } other { relazioni } } su {entities} { entities, plural, one { voce } other { voci } } {count, plural, one { non è } other { non sono } } ancora pubblicata e potrebbe portare a comportamenti inaspettati. ",
  "popUpWarning.warning.publish-question": "Vuoi ancora pubblicare?",
  "popUpWarning.warning.unpublish": "Se non pubblichi questo contenuto, diventerà automaticamente una Bozza.",
  "popUpWarning.warning.unpublish-question": "Sei sicuro di non volerlo pubblicare?",
  "popUpWarning.warning.updateAllSettings": "Questo modificherà tutte le tue impostazioni",
  "popover.display-relations.label": "Visualizza relazioni",
  "preview.panel.title": "Anteprima",
  "preview.panel.button": "Apri anteprima",
  "preview.panel.button-disabled-tooltip": "Salva per aprire l'anteprima",
  "preview.page-title": "Anteprima {contentType}",
  "preview.header.close": "Chiudi anteprima",
  "preview.copy.label": "Copia link anteprima",
  "preview.copy.success": "Link anteprima copiato",
  "preview.tabs.label": "Stato anteprima",
  "preview.content.close-editor": "Chiudi editor",
  "preview.content.open-editor": "Apri editor",
  "relation.create": "Crea una relazione",
  "relation.add": "Aggiungi o crea una relazione",
  "relation.disconnect": "Rimuovi",
  "relation.error-adding-relation": "Si è verificato un errore durante il tentativo di aggiungere la relazione.",
  "relation.isLoading": "Le relazioni si stanno caricando",
  "relation.loadMore": "Carica Altro",
  "relation.notAvailable": "Nessuna relazione disponibile",
  "relation.publicationState.draft": "Bozza",
  "relation.publicationState.published": "Pubblicato",
  "reviewWorkflows.stage.label": "Fase di revisione",
  "select.currently.selected": "{count} attualmente selezionati",
  "success.record.clone": "Documento clonato",
  "success.record.discard": "Modifiche scartate",
  "success.record.delete": "Documento eliminato",
  "success.record.publish": "Documento pubblicato",
  "success.record.publishing": "Pubblicazione in corso...",
  "success.record.save": "Documento salvato",
  "success.record.unpublish": "Pubblicazione del documento annullata",
  "success.records.delete": "Eliminato con successo.",
  "success.records.unpublish": "Pubblicazione annullata con successo.",
  "success.records.publish": "Pubblicato con successo.",
  "utils.data-loaded": "{number, plural, =1 {La voce è stata} other {Le voci sono state}} caricata/e con successo",
  "listView.validation.errors.title": "Azione richiesta",
  "listView.validation.errors.message": "Assicurati che tutti i campi siano validi prima di pubblicare (campo obbligatorio, limite minimo/massimo di caratteri, ecc.)",
  "history.document-action": "Cronologia dei Contenuti",
  "history.page-title": "Cronologia {contentType}",
  "history.sidebar.title": "Versioni",
  "history.sidebar.version-card.aria-label": "Scheda versione",
  "history.sidebar.versionDescription": "{distanceToNow}{isAnonymous, select, true {} other { da {author}}}{isCurrent, select, true { (attuale)} other {}}",
  "history.sidebar.show-newer": "Mostra versioni più recenti",
  "history.sidebar.show-older": "Mostra versioni più vecchie",
  "history.version.subtitle": "{hasLocale, select, true {{subtitle}, in {locale}} other {{subtitle}}}",
  "history.content.new-field.title": "Nuovo campo",
  "history.content.new-field.message": "Questo campo non esisteva quando questa versione è stata salvata. Se ripristini questa versione, sarà vuoto.",
  "history.content.unknown-fields.title": "Campi sconosciuti",
  "history.content.unknown-fields.message": "Questi campi sono stati eliminati o rinominati nel Costruttore di Tipi di Contenuto. Questi campi non verranno ripristinati.",
  "history.content.missing-assets.title": "{number, plural, =1 {Asset mancante} other {{number} asset mancanti}}",
  "history.content.missing-assets.message": "{number, plural, =1 {È stato} other {Sono stati}} eliminato/i nella Libreria Multimediale e non può/possono essere ripristinato/i.",
  "history.content.missing-relations.title": "{number, plural, =1 {Relazione mancante} other {{number} relazioni mancanti}}",
  "history.content.missing-relations.message": "{number, plural, =1 {È stata} other {Sono state}} eliminata/e e non può/possono essere ripristinata/e.",
  "history.content.no-relations": "Nessuna relazione.",
  "history.content.localized": "Questo valore è specifico per questa lingua. Se ripristini questa versione, il contenuto non sarà sostituito per le altre lingue.",
  "history.content.not-localized": "Questo valore è comune a tutte le lingue. Se ripristini questa versione, il contenuto sarà sostituito per tutte le lingue.",
  "history.restore.confirm.button": "Ripristina",
  "history.restore.confirm.title": "Sei sicuro di voler ripristinare questa versione?",
  "history.restore.confirm.message": "{isDraft, select, true {Il contenuto ripristinato sovrascriverà la tua bozza.} other {Il contenuto ripristinato non sarà pubblicato, sovrascriverà la bozza e sarà salvato come modifiche in sospeso. Potrai pubblicare le modifiche in qualsiasi momento.}}",
  "history.restore.success.title": "Versione ripristinata.",
  "history.restore.success.message": "Una versione passata del contenuto è stata ripristinata.",
  "history.restore.error.message": "Impossibile ripristinare la versione.",
  "validation.error": "Ci sono errori di validazione nel tuo documento. Per favore correggili prima di salvare.",
  "bulk-publish.edit": "Modifica",
  "widget.last-edited.title": "Ultime voci modificate",
  "widget.last-edited.single-type": "Tipo Singolo",
  "widget.last-edited.no-data": "Nessuna voce modificata",
  "widget.last-published.title": "Ultime voci pubblicate",
  "widget.last-published.no-data": "Nessuna voce pubblicata",
  "attribute.boolean": "Booleano",
  "attribute.boolean.description": "Sì o no, 1 o 0, vero o falso",
  "attribute.component": "Componente",
  "attribute.component.description": "Gruppo di campi che puoi ripetere o riutilizzare",
  "attribute.customField": "Campo personalizzato",
  "attribute.date": "Data",
  "attribute.date.description": "Un selettore di data con ore, minuti e secondi",
  "attribute.datetime": "Data e ora",
  "attribute.dynamiczone": "Zona dinamica",
  "attribute.dynamiczone.description": "Scegli dinamicamente il componente durante la modifica del contenuto",
  "attribute.email": "Email",
  "attribute.email.description": "Campo email con validazione del formato",
  "attribute.enumeration": "Enumerazione",
  "attribute.enumeration.description": "Lista di valori, poi scegli uno",
  "attribute.json": "JSON",
  "attribute.json.description": "Dati in formato JSON",
  "attribute.media": "Media",
  "attribute.media.description": "File come immagini, video, ecc.",
  "attribute.null": " ",
  "attribute.number": "Numero",
  "attribute.number.description": "Numeri (intero, float, decimale)",
  "attribute.password": "Password",
  "attribute.password.description": "Campo password con crittografia",
  "attribute.relation": "Relazione",
  "attribute.relation.description": "Si riferisce a un Tipo di Collezione",
  "attribute.richtext": "Testo ricco (Markdown)",
  "attribute.richtext.description": "Il classico editor di testo ricco",
  "attribute.blocks": "Testo ricco (Blocchi)",
  "attribute.blocks.description": "Il nuovo editor di testo ricco basato su JSON",
  "attribute.text": "Testo",
  "attribute.text.description": "Testo breve o lungo come titolo o descrizione",
  "attribute.time": "Ora",
  "attribute.timestamp": "Timestamp",
  "attribute.uid": "UID",
  "attribute.uid.description": "Identificatore unico",
  "button.attributes.add.another": "Aggiungi un altro campo",
  "button.component.add": "Aggiungi un componente",
  "button.component.create": "Crea nuovo componente",
  "button.model.create": "Crea nuovo tipo di collezione",
  "button.single-types.create": "Crea nuovo tipo singolo",
  "component.repeatable": "(ripetibile)",
  "components.SelectComponents.displayed-value": "{number, plural, =0 {# componenti} one {# componente} other {# componenti}} selezionati",
  "components.componentSelect.no-component-available": "Hai già aggiunto tutti i tuoi componenti",
  "components.componentSelect.no-component-available.with-search": "Non c'è nessun componente che corrisponda alla tua ricerca",
  "components.componentSelect.value-component": "{number} componente selezionato (digita per cercare un componente)",
  "components.componentSelect.value-components": "{number} componenti selezionati",
  "configurations": "Configurazioni",
  "contentType.apiId-plural.description": "ID API pluralizzato",
  "contentType.apiId-plural.label": "ID API (Plurale)",
  "contentType.apiId-singular.description": "L'UID viene utilizzato per generare le rotte API e le tabelle/collezioni del database",
  "contentType.apiId-singular.label": "ID API (Singolare)",
  "contentType.collectionName.description": "Utile quando il nome del tuo Tipo di Contenuto e il nome della tua tabella differiscono",
  "contentType.collectionName.label": "Nome della collezione",
  "contentType.displayName.label": "Nome visualizzato",
  "contentType.kind.change.warning": "Hai appena cambiato il tipo di un tipo di contenuto: l'API verrà resettata (rotte, controller e servizi saranno sovrascritti).",
  "error.attributeName.reserved-name": "Questo nome non può essere utilizzato nel tuo tipo di contenuto in quanto potrebbe interrompere altre funzionalità",
  "error.contentType.pluralName-used": "Questo valore non può essere lo stesso di quello singolare",
  "error.contentType.singularName-used": "Questo valore non può essere lo stesso di quello plurale",
  "error.contentType.singularName-equals-pluralName": "Questo valore non può essere lo stesso dell'ID API Plurale di un altro tipo di contenuto.",
  "error.contentType.pluralName-equals-singularName": "Questo valore non può essere lo stesso dell'ID API Singolare di un altro tipo di contenuto.",
  "error.contentType.pluralName-equals-collectionName": "Questo valore è già in uso da un altro tipo di contenuto.",
  "error.contentTypeName.reserved-name": "Questo nome non può essere utilizzato nel tuo progetto in quanto potrebbe interrompere altre funzionalità",
  "error.validation.enum-duplicate": "I valori duplicati non sono consentiti (solo i caratteri alfanumerici vengono presi in considerazione).",
  "error.validation.enum-empty-string": "Le stringhe vuote non sono consentite",
  "error.validation.enum-regex": "Almeno un valore non è valido. I valori dovrebbero avere almeno un carattere alfabetico che precede la prima occorrenza di un numero.",
  "error.validation.positive": "Deve essere un numero positivo",
  "error.validation.relation.targetAttribute-taken": "Questo nome esiste nel target",
  "form.attribute.component.option.add": "Aggiungi un componente",
  "form.attribute.component.option.create": "Crea un nuovo componente",
  "form.attribute.component.option.create.description": "Un componente è condiviso tra tipi e componenti, sarà disponibile e accessibile ovunque.",
  "form.attribute.component.option.repeatable": "Componente ripetibile",
  "form.attribute.component.option.repeatable.description": "Ideale per istanze multiple (array) di ingredienti, meta tag, ecc.",
  "form.attribute.component.option.reuse-existing": "Usa un componente esistente",
  "form.attribute.component.option.reuse-existing.description": "Riutilizza un componente già creato per mantenere i tuoi dati coerenti tra i tipi di contenuto.",
  "form.attribute.component.option.single": "Componente singolo",
  "form.attribute.component.option.single.description": "Ideale per raggruppare campi come indirizzo completo, informazioni principali, ecc.",
  "form.attribute.item.customColumnName": "Nomi di colonna personalizzati",
  "form.attribute.item.customColumnName.description": "Questo è utile per rinominare le colonne del database in un formato più comprensibile per le risposte delle API",
  "form.attribute.item.date.type.date": "data (es: 01/01/{currentYear})",
  "form.attribute.item.date.type.datetime": "data e ora (es: 01/01/{currentYear} 00:00 AM)",
  "form.attribute.item.date.type.time": "ora (es: 00:00 AM)",
  "form.attribute.item.defineRelation.fieldName": "Nome del campo",
  "form.attribute.item.enumeration.graphql": "Sovrascrittura del nome per GraphQL",
  "form.attribute.item.enumeration.graphql.description": "Ti permette di sovrascrivere il nome generato di default per GraphQL",
  "form.attribute.item.enumeration.placeholder": "Es:nmattinanmezzogiornonsera",
  "form.attribute.item.enumeration.rules": "Valori (uno per riga)",
  "form.attribute.item.maximum": "Valore massimo",
  "form.attribute.item.maximumLength": "Lunghezza massima",
  "form.attribute.item.minimum": "Valore minimo",
  "form.attribute.item.minimumLength": "Lunghezza minima",
  "form.attribute.item.number.type": "Formato del numero",
  "form.attribute.item.number.type.biginteger": "intero grande (es: 123456789)",
  "form.attribute.item.number.type.decimal": "decimale (es: 2.22)",
  "form.attribute.item.number.type.float": "float (es: 3.33333333)",
  "form.attribute.item.number.type.integer": "intero (es: 10)",
  "form.attribute.item.privateField": "Campo privato",
  "form.attribute.item.privateField.description": "Questo campo non apparirà nella risposta API",
  "form.attribute.item.requiredField": "Campo obbligatorio",
  "form.attribute.item.requiredField.description": "Non potrai creare una voce se questo campo è vuoto",
  "form.attribute.item.text.regex": "Pattern RegExp",
  "form.attribute.item.text.regex.description": "Il testo dell'espressione regolare",
  "form.attribute.item.uniqueField": "Campo unico",
  "form.attribute.item.uniqueField.description": "Non potrai creare una voce se esiste già una voce con contenuto identico",
  "form.attribute.item.uniqueField.v5.willBeDisabled'": "Attualmente i campi unici non funzionano correttamente nei componenti. Se disabiliti questa funzionalità, il campo sarà disabilitato fino a quando non sarà risolto.",
  "form.attribute.item.uniqueField.v5.disabled": "Attualmente i campi unici non funzionano correttamente nei componenti. Questo campo è stato disabilitato fino a quando non sarà risolto.",
  "form.attribute.media.allowed-types": "Seleziona i tipi di media consentiti",
  "form.attribute.media.allowed-types.option-files": "File",
  "form.attribute.media.allowed-types.option-images": "Immagini",
  "form.attribute.media.allowed-types.option-videos": "Video",
  "form.attribute.media.option.multiple": "Media multipli",
  "form.attribute.media.option.multiple.description": "Ideale per slider, caroselli o download di file multipli",
  "form.attribute.media.option.single": "Media singolo",
  "form.attribute.media.option.single.description": "Ideale per avatar, foto profilo o copertina",
  "form.attribute.settings.default": "Valore predefinito",
  "form.attribute.text.option.long-text": "Testo lungo",
  "form.attribute.text.option.long-text.description": "Ideale per descrizioni, biografie. La ricerca esatta è disabilitata.",
  "form.attribute.text.option.short-text": "Testo breve",
  "form.attribute.text.option.short-text.description": "Ideale per titoli, nomi, link (URL). Abilita anche la ricerca esatta sul campo.",
  "form.button.add-components-to-dynamiczone": "Aggiungi componenti alla zona",
  "form.button.add-field": "Aggiungi un altro campo",
  "form.button.add-first-field-to-created-component": "Aggiungi il primo campo al componente",
  "form.button.add.field.to.collectionType": "Aggiungi un altro campo a questo tipo di collezione",
  "form.button.add.field.to.component": "Aggiungi un altro campo a questo componente",
  "form.button.add.field.to.contentType": "Aggiungi un altro campo a questo tipo di contenuto",
  "form.button.add.field.to.singleType": "Aggiungi un altro campo a questo tipo singolo",
  "form.button.cancel": "Annulla",
  "form.button.collection-type.description": "Ideale per istanze multiple come articoli, prodotti, commenti, ecc.",
  "form.button.collection-type.name": "Tipo di Collezione",
  "form.button.configure-component": "Configura il componente",
  "form.button.configure-view": "Configura la vista",
  "form.button.select-component": "Seleziona un componente",
  "form.button.single-type.description": "Ideale per istanze singole come about us, homepage, ecc.",
  "form.button.single-type.name": "Tipo Singolo",
  "from": "da",
  "listView.headerLayout.description": "Costruisci l'architettura dei dati del tuo contenuto",
  "menu.section.components.name": "Componenti",
  "menu.section.models.name": "Tipi di Collezione",
  "menu.section.single-types.name": "Tipi Singoli",
  "modalForm.attribute.form.base.name.description": "Non sono consentiti spazi per il nome dell'attributo",
  "modalForm.attribute.form.base.name.placeholder": "es. slug, seoUrl, canonicalUrl",
  "modalForm.attribute.target-field": "Campo collegato",
  "modalForm.attributes.select-component": "Seleziona un componente",
  "modalForm.attributes.select-components": "Seleziona i componenti",
  "modalForm.collectionType.header-create": "Crea un tipo di collezione",
  "modalForm.component.header-create": "Crea un componente",
  "modalForm.components.create-component.category.label": "Seleziona una categoria o inserisci un nome per crearne una nuova",
  "modalForm.components.icon.label": "Icona",
  "modalForm.empty.button": "Aggiungi campi personalizzati",
  "modalForm.empty.heading": "Non c'è ancora nulla qui.",
  "modalForm.empty.sub-heading": "Trova ciò che stai cercando attraverso una vasta gamma di estensioni.",
  "modalForm.editCategory.base.name.description": "Non sono consentiti spazi per il nome della categoria",
  "modalForm.header-edit": "Modifica {name}",
  "modalForm.header.categories": "Categorie",
  "modalForm.header.back": "Indietro",
  "modalForm.singleType.header-create": "Crea un tipo singolo",
  "modalForm.sub-header.addComponentToDynamicZone": "Aggiungi nuovo componente alla zona dinamica",
  "modalForm.sub-header.attribute.create": "Aggiungi nuovo campo {type}",
  "modalForm.sub-header.attribute.create.step": "Aggiungi nuovo componente ({step}/2)",
  "modalForm.sub-header.attribute.edit": "Modifica {name}",
  "modalForm.sub-header.chooseAttribute.collectionType": "Seleziona un campo per il tuo tipo di collezione",
  "modalForm.sub-header.chooseAttribute.component": "Seleziona un campo per il tuo componente",
  "modalForm.sub-header.chooseAttribute.singleType": "Seleziona un campo per il tuo tipo singolo",
  "modalForm.custom-fields.advanced.settings.extended": "Impostazioni estese",
  "modalForm.tabs.custom": "Personalizzato",
  "modalForm.tabs.custom.howToLink": "Come aggiungere campi personalizzati",
  "modalForm.tabs.default": "Predefinito",
  "modalForm.tabs.label": "Schede tipi predefiniti e personalizzati",
  "modelPage.attribute.relation-polymorphic": "Relazione (polimorfica)",
  "modelPage.attribute.relationWith": "Relazione con",
  "notification.error.dynamiczone-min.validation": "È richiesto almeno un componente in una zona dinamica per poter salvare un tipo di contenuto",
  "notification.info.autoreaload-disable": "Strapi è in modalità produzione, la modifica dei tipi di contenuto è disabilitata. Si prega di passare alla modalità di sviluppo avviando il server con strapi develop.",
  "notification.info.creating.notSaved": "Si prega di salvare il lavoro prima di creare un nuovo tipo di collezione o componente",
  "plugin.name": "Costruttore di Tipi di Contenuto",
  "popUpForm.navContainer.advanced": "Impostazioni avanzate",
  "popUpForm.navContainer.base": "Impostazioni di base",
  "popUpWarning.bodyMessage.cancel-modifications": "Sei sicuro di voler annullare le tue modifiche?",
  "popUpWarning.bodyMessage.cancel-modifications.with-components": "Sei sicuro di voler annullare le tue modifiche? Alcuni componenti sono stati creati o modificati...",
  "popUpWarning.bodyMessage.category.delete": "Sei sicuro di voler eliminare questa categoria? Tutti i componenti saranno eliminati.",
  "popUpWarning.bodyMessage.component.delete": "Sei sicuro di voler eliminare questo componente?",
  "popUpWarning.draft-publish.button.confirm": "Sì, disabilita",
  "popUpWarning.draft-publish.message": "Se disabiliti la funzione Bozza & pubblica, le tue bozze verranno eliminate.",
  "popUpWarning.draft-publish.second-message": "Sei sicuro di volerla disabilitare?",
  "prompt.unsaved": "Sei sicuro di voler uscire? Tutte le tue modifiche andranno perse.",
  "relation.attributeName.placeholder": "Es: autore, categoria, tag",
  "relation.manyToMany": "ha e appartiene a molti",
  "relation.manyToOne": "ha molti",
  "relation.manyWay": "ha molti",
  "relation.oneToMany": "appartiene a molti",
  "relation.oneToOne": "ha e appartiene a uno",
  "relation.oneWay": "ha uno",
  "table.button.no-fields": "Aggiungi nuovo campo",
  "table.content.create-first-content-type": "Crea il tuo primo Tipo di Collezione",
  "table.content.no-fields.collection-type": "Aggiungi il tuo primo campo a questo Tipo di Collezione",
  "table.content.no-fields.component": "Aggiungi il tuo primo campo a questo componente",
  "IconPicker.search.placeholder.label": "Cerca un'icona",
  "IconPicker.search.clear.label": "Cancella la ricerca dell'icona",
  "IconPicker.search.button.label": "Pulsante di ricerca icona",
  "IconPicker.remove.tooltip": "Rimuovi l'icona selezionata",
  "IconPicker.remove.button": "Pulsante per rimuovere l'icona selezionata",
  "IconPicker.emptyState.label": "Nessuna icona trovata",
  "IconPicker.icon.label": "Seleziona l'icona {icon}"
}